locker_admin-0.1.29.data/scripts/locker-admin
locker_client/__init__.py
locker_client/version.py
locker_admin-0.1.29.dist-info/LICENSE
locker_admin-0.1.29.dist-info/METADATA
locker_admin-0.1.29.dist-info/WHEEL
locker_admin-0.1.29.dist-info/top_level.txt
locker_admin-0.1.29.dist-info/RECORD
