Metadata-Version: 2.1
Name: locker-admin
Version: 0.1.29
Summary: locker-admin
Home-page: https://github.com/yaroslaff/locker-admin
Author: Yaroslav Polyakov
Author-email: yaroslaff@gmail.com
License: MIT
Platform: UNKNOWN
Requires-Dist: flask-socketio
Requires-Dist: loguru
Requires-Dist: python-dotenv
Requires-Dist: requests
